Workbook

Sheet README
A1: US Airline Share Repurchases: A Capital Allocation Scorecard
A3: Question
A4: Six US airlines spent $49.1 billion repurchasing their own shares between 2015 and 2026.
A5: Treating every repurchase as an investment, what return did that capital earn, and how does it compare to the alternatives available at the time?
A7: Findings
A8: $49.1bn spent, worth $55.4bn as of Sept 2026 — roughly 1% a year.
A9: Timing was not the problem: five of six carriers beat an even-spread benchmark.
A10: Four of six lost to simply repaying debt. All six lost to the S&P 500.
A11: American: 5.2x leverage at YE2019, the only negative timing alpha, $13.5bn destroyed.
A13: Carriers
A14: American (AAL), Alaska (ALK), Delta (DAL), JetBlue (JBLU), Southwest (LUV), United (UAL)
A16: Data sources
... A51: Prices as of September 4, 2026. All results move with the market.

Sheet buybacks
A1: ticker | B1: fiscal_year | C1: quarter | D1: period_end | E1: buyback_musd | F1: method | G1: note | H1: key | I1: avg_price | J1: current_price | K1: shares_bought | L1: value_today | M1: weighted_date | N1: spy_key | O1: spy_price | P1: spy_shares | Q1: spy_value_today | R1: years_from_quarter | S1: debt_value_today | T1: is_active | U1: active_count | V1: even_spend | W1: even_shares | X1: even_value_today
A2: AAL | B2: 2015 | C2: Q1 | D2: 42094 | E2: 181 | F2: ytd_difference | G2: =IF(F2<>"missing","",IF(D2>DATE(2026,6,30),"not yet filed","no repurchases reported")) | H2: =A2&"-"&B2&"-"&C2 -> AAL-2015-Q1 | I2: =_xlfn.XLOOKUP(H2,prices!A:A,prices!F:F,"no match") -> 48.17 | J2: =_xlfn.XLOOKUP(A2,current!$A:$A,current!$B:$B,"no match") -> 13.13 | K2: =IF(E2="","",E2*1000000/I2) -> 3757525.4 | L2: =IF(K2="","",K2*J2) -> 49336309 | M2: =IF(E2="","",E2*D2) -> 7619014 | N2: ="SPY-"&B2&"-"&C2 -> SPY-2015-Q1 | O2: =_xlfn.XLOOKUP(N2,prices!$A:$A,prices!$F:$F,"no match") -> 170.57 | P2: =IF(E2="","",E2*1000000/O2) -> 1061147.9 | Q2: =IF(P2="","",P2*assumptions!$B$4) -> 8.1728551e+08 | R2: =IF(E2="","",(TODAY()-D2)/365.25) -> 11.441478 | S2: =IF(E2="","",E2*1000000*(1+assumptions!$B$3)^R2) -> 2.8195231e+08 | T2: =IF(E2="",0,IF(E2>0,1,0)) -> 1 | U2: =SUMIFS($T:$T,$A:$A,$A2) -> 23 | V2: =IF(T2=0,0,SUMIFS($E:$E,$A:$A,$A2)/U2) -> 526.3913 | W2: =IF(V2=0,0,V2*1000000/I2) -> 10927783 | X2: =IF(W2=0,0,W2*J2) -> 1.4348179e+08
A3: AAL | B3: 2015 | C3: Q2 | D3: 42185 | E3: 750 | F3: ytd_difference | G3: =IF(F3<>"missing","",IF(D3>DATE(2026,6,30),"not yet filed","no repurchases reported")) | H3: =A3&"-"&B3&"-"&C3 -> AAL-2015-Q2 | I3: =_xlfn.XLOOKUP(H3,prices!A:A,prices!F:F,"no match") -> 43.35 | J3: =_xlfn.XLOOKUP(A3,current!$A:$A,current!$B:$B,"no match") -> 13.13 | K3: =IF(E3="","",E3*1000000/I3) -> 17301038 | L3: =IF(K3="","",K3*J3) -> 2.2716263e+08 | M3: =IF(E3="","",E3*D3) -> 31638750 | N3: ="SPY-"&B3&"-"&C3 -> SPY-2015-Q2 | O3: =_xlfn.XLOOKUP(N3,prices!$A:$A,prices!$F:$F,"no match") -> 174.56 | P3: =IF(E3="","",E3*1000000/O3) -> 4296517 | Q3: =IF(P3="","",P3*assumptions!$B$4) -> 3.3091344e+09 | R3: =IF(E3="","",(TODAY()-D3)/365.25) -> 11.192334 | S3: =IF(E3="","",E3*1000000*(1+assumptions!$B$3)^R3) -> 1.1570886e+09 | T3: =IF(E3="",0,IF(E3>0,1,0)) -> 1 | U3: =SUMIFS($T:$T,$A:$A,$A3) -> 23 | V3: =IF(T3=0,0,SUMIFS($E:$E,$A:$A,$A3)/U3) -> 526.3913 | W3: =IF(V3=0,0,V3*1000000/I3) -> 12142821 | X3: =IF(W3=0,0,W3*J3) -> 1.5943524e+08
A4: AAL | B4: 2015 | C4: Q3 | D4: 42277 | E4: 1480 | F4: ytd_difference | G4: =IF(F4<>"missing","",IF(D4>DATE(2026,6,30),"not yet filed","no repurchases reported")) | H4: =A4&"-"&B4&"-"&C4 -> AAL-2015-Q3 | I4: =_xlfn.XLOOKUP(H4,prices!A:A,prices!F:F,"no match") -> 39.12 | J4: =_xlfn.XLOOKUP(A4,current!$A:$A,current!$B:$B,"no match") -> 13.13 | K4: =IF(E4="","",E4*1000000/I4) -> 37832311 | L4: =IF(K4="","",K4*J4) -> 4.9673824e+08 | M4: =IF(E4="","",E4*D4) -> 62569960 | N4: ="SPY-"&B4&"-"&C4 -> SPY-2015-Q3 | O4: =_xlfn.XLOOKUP(N4,prices!$A:$A,prices!$F:$F,"no match") -> 169.23 | P4: =IF(E4="","",E4*1000000/O4) -> 8745494.3 | Q4: =IF(P4="","",P4*assumptions!$B$4) -> 6.7356923e+09 | R4: =IF(E4="","",(TODAY()-D4)/365.25) -> 10.940452 | S4: =IF(E4="","",E4*1000000*(1+assumptions!$B$3)^R4) -> 2.2611495e+09 | T4: =IF(E4="",0,IF(E4>0,1,0)) -> 1 | U4: =SUMIFS($T:$T,$A:$A,$A4) -> 23 | V4: =IF(T4=0,0,SUMIFS($E:$E,$A:$A,$A4)/U4) -> 526.3913 | W4: =IF(V4=0,0,V4*1000000/I4) -> 13455810 | X4: =IF(W4=0,0,W4*J4) -> 1.7667479e+08
A5: AAL | B5: 2015 | C5: Q4 | D5: 42369 | E5: 1435 | F5: ytd_difference | G5: =IF(F5<>"missing","",IF(D5>DATE(2026,6,30),"not yet filed","no repurchases reported")) | H5: =A5&"-"&B5&"-"&C5 -> AAL-2015-Q4 | I5: =_xlfn.XLOOKUP(H5,prices!A:A,prices!F:F,"no match") -> 41.38 | J5: =_xlfn.XLOOKUP(A5,current!$A:$A,current!$B:$B,"no match") -> 13.13 | K5: =IF(E5="","",E5*1000000/I5) -> 34678589 | L5: =IF(K5="","",K5*J5) -> 4.5532987e+08 | M5: =IF(E5="","",E5*D5) -> 60799515 | N5: ="SPY-"&B5&"-"&C5 -> SPY-2015-Q4 | O5: =_xlfn.XLOOKUP(N5,prices!$A:$A,prices!$F:$F,"no match") -> 172.25 | P5: =IF(E5="","",E5*1000000/O5) -> 8330914.4 | Q5: =IF(P5="","",P5*assumptions!$B$4) -> 6.4163869e+09 | R5: =IF(E5="","",(TODAY()-D5)/365.25) -> 10.688569 | S5: =IF(E5="","",E5*1000000*(1+assumptions!$B$3)^R5) -> 2.1711092e+09 | T5: =IF(E5="",0,IF(E5>0,1,0)) -> 1 | U5: =SUMIFS($T:$T,$A:$A,$A5) -> 23 | V5: =IF(T5=0,0,SUMIFS($E:$E,$A:$A,$A5)/U5) -> 526.3913 | W5: =IF(V5=0,0,V5*1000000/I5) -> 12720911 | X5: =IF(W5=0,0,W5*J5) -> 1.6702556e+08
A6: AAL | B6: 2016 | C6: Q1 | D6: 42460 | E6: 1525 | F6: ytd_difference | G6: =IF(F6<>"missing","",IF(D6>DATE(2026,6,30),"not yet filed","no repurchases reported")) | H6: =A6&"-"&B6&"-"&C6 -> AAL-2016-Q1 | I6: =_xlfn.XLOOKUP(H6,prices!A:A,prices!F:F,"no match") -> 38.53 | J6: =_xlfn.XLOOKUP(A6,current!$A:$A,current!$B:$B,"no match") -> 13.13 | K6: =IF(E6="","",E6*1000000/I6) -> 39579548 | L6: =IF(K6="","",K6*J6) -> 5.1967947e+08 | M6: =IF(E6="","",E6*D6) -> 64751500 | N6: ="SPY-"&B6&"-"&C6 -> SPY-2016-Q1 | O6: =_xlfn.XLOOKUP(N6,prices!$A:$A,prices!$F:$F,"no match") -> 164.64 | P6: =IF(E6="","",E6*1000000/O6) -> 9262633.6 | Q6: =IF(P6="","",P6*assumptions!$B$4) -> 7.1339878e+09 | R6: =IF(E6="","",(TODAY()-D6)/365.25) -> 10.439425 | S6: =IF(E6="","",E6*1000000*(1+assumptions!$B$3)^R6) -> 2.2851141e+09 | T6: =IF(E6="",0,IF(E6>0,1,0)) -> 1 | U6: =SUMIFS($T:$T,$A:$A,$A6) -> 23 | V6: =IF(T6=0,0,SUMIFS($E:$E,$A:$A,$A6)/U6) -> 526.3913 | W6: =IF(V6=0,0,V6*1000000/I6) -> 13661856 | X6: =IF(W6=0,0,W6*J6) -> 1.7938017e+08
A7: AAL | B7: 2016 | C7: Q2 | D7: 42551 | E7: 1711 | F7: ytd_difference | G7: =IF(F7<>"missing","",IF(D7>DATE(2026,6,30),"not yet filed","no repurchases reported")) | H7: =A7&"-"&B7&"-"&C7 -> AAL-2016-Q2 | I7: =_xlfn.XLOOKUP(H7,prices!A:A,prices!F:F,"no match") -> 32.44 | J7: =_xlfn.XLOOKUP(A7,current!$A:$A,current!$B:$B,"no match") -> 13.13 | K7: =IF(E7="","",E7*1000000/I7) -> 52743527 | L7: =IF(K7="","",K7*J7) -> 6.925225e+08 | M7: =IF(E7="","",E7*D7) -> 72804761 | N7: ="SPY-"&B7&"-"&C7 -> SPY-2016-Q2 | O7: =_xlfn.XLOOKUP(N7,prices!$A:$A,prices!$F:$F,"no match") -> 175.97 | P7: =IF(E7="","",E7*1000000/O7) -> 9723248.3 | Q7: =IF(P7="","",P7*assumptions!$B$4) -> 7.4887486e+09 | R7: =IF(E7="","",(TODAY()-D7)/365.25) -> 10.190281 | S7: =IF(E7="","",E7*1000000*(1+assumptions!$B$3)^R7) -> 2.5391966e+09 | T7: =IF(E7="",0,IF(E7>0,1,0)) -> 1 | U7: =SUMIFS($T:$T,$A:$A,$A7) -> 23 | V7: =IF(T7=0,0,SUMIFS($E:$E,$A:$A,$A7)/U7) -> 526.3913 | W7: =IF(V7=0,0,V7*1000000/I7) -> 16226612 | X7: =IF(W7=0,0,W7*J7) -> 2.1305542e+08
A8: AAL | B8: 2016 | C8: Q3 | D8: 42643 | E8: 695 | F8: ytd_difference | G8: =IF(F8<>"missing","",IF(D8>DATE(2026,6,30),"not yet filed","no repurchases reported")) | H8: =A8&"-"&B8&"-"&C8 -> AAL-2016-Q3 | I8: =_xlfn.XLOOKUP(H8,prices!A:A,prices!F:F,"no match") -> 34.02 | J8: =_xlfn.XLOOKUP(A8,current!$A:$A,current!$B:$B,"no match") -> 13.13 | K8: =IF(E8="","",E8*1000000/I8) -> 20429159 | L8: =IF(K8="","",K8*J8) -> 2.6823486e+08 | M8: =IF(E8="","",E8*D8) -> 29636885 | N8: ="SPY-"&B8&"-"&C8 -> SPY-2016-Q3 | O8: =_xlfn.XLOOKUP(N8,prices!$A:$A,prices!$F:$F,"no match") -> 184.28 | P8: =IF(E8="","",E8*1000000/O8) -> 3771434.8 | Q8: =IF(P8="","",P8*assumptions!$B$4) -> 2.9047213e+09 | R8: =IF(E8="","",(TODAY()-D8)/365.25) -> 9.9383984 | S8: =IF(E8="","",E8*1000000*(1+assumptions!$B$3)^R8) -> 1.0213941e+09 | T8: =IF(E8="",0,IF(E8>0,1,0)) -> 1 | U8: =SUMIFS($T:$T,$A:$A,$A8) -> 23 | V8: =IF(T8=0,0,SUMIFS($E:$E,$A:$A,$A8)/U8) -> 526.3913 | W8: =IF(V8=0,0,V8*1000000/I8) -> 15472995 | X8: =IF(W8=0,0,W8*J8) -> 2.0316043e+08
A9: AAL | B9: 2016 | C9: Q4 | D9: 42735 | E9: 569 | F9: ytd_difference | G9: =IF(F9<>"missing","",IF(D9>DATE(2026,6,30),"not yet filed","no repurchases reported")) | H9: =A9&"-"&B9&"-"&C9 -> AAL-2016-Q4 | I9: =_xlfn.XLOOKUP(H9,prices!A:A,prices!F:F,"no match") -> 42.05 | J9: =_xlfn.XLOOKUP(A9,current!$A:$A,current!$B:$B,"no match") -> 13.13 | K9: =IF(E9="","",E9*1000000/I9) -> 13531510 | L9: =IF(K9="","",K9*J9) -> 1.7766873e+08 | M9: =IF(E9="","",E9*D9) -> 24316215 | N9: ="SPY-"&B9&"-"&C9 -> SPY-2016-Q4 | O9: =_xlfn.XLOOKUP(N9,prices!$A:$A,prices!$F:$F,"no match") -> 187.21 | P9: =IF(E9="","",E9*1000000/O9) -> 3039367.6 | Q9: =IF(P9="","",P9*assumptions!$B$4) -> 2.3408905e+09 | R9: =IF(E9="","",(TODAY()-D9)/365.25) -> 9.6865161 | S9: =IF(E9="","",E9*1000000*(1+assumptions!$B$3)^R9) -> 8.281004e+08 | T9: =IF(E9="",0,IF(E9>0,1,0)) -> 1 | U9: =SUMIFS($T:$T,$A:$A,$A9) -> 23 | V9: =IF(T9=0,0,SUMIFS($E:$E,$A:$A,$A9)/U9) -> 526.3913 | W9: =IF(V9=0,0,V9*1000000/I9) -> 12518224 | X9: =IF(W9=0,0,W9*J9) -> 1.6436428e+08
A10: AAL | B10: 2017 | C10: Q1 | D10: 42825 | E10: 484 | F10: ytd_difference | G10: =IF(F10<>"missing","",IF(D10>DATE(2026,6,30),"not yet filed","no repurchases reported")) | H10: =A10&"-"&B10&"-"&C10 -> AAL-2017-Q1 | I10: =_xlfn.XLOOKUP(H10,prices!A:A,prices!F:F,"no match") -> 43.78 | J10: =_xlfn.XLOOKUP(A10,current!$A:$A,current!$B:$B,"no match") -> 13.13 | K10: =IF(E10="","",E10*1000000/I10) -> 11055276 | L10: =IF(K10="","",K10*J10) -> 1.4515578e+08 | M10: =IF(E10="","",E10*D10) -> 20727300 | N10: ="SPY-"&B10&"-"&C10 -> SPY-2017-Q1 | O10: =_xlfn.XLOOKUP(N10,prices!$A:$A,prices!$F:$F,"no match") -> 200.26 | P10: =IF(E10="","",E10*1000000/O10) -> 2416858.1 | Q10: =IF(P10="","",P10*assumptions!$B$4) -> 1.8614399e+09 | R10: =IF(E10="","",(TODAY()-D10)/365.25) -> 9.4401095 | S10: =IF(E10="","",E10*1000000*(1+assumptions!$B$3)^R10) -> 6.9770273e+08 | T10: =IF(E10="",0,IF(E10>0,1,0)) -> 1 | U10: =SUMIFS($T:$T,$A:$A,$A10) -> 23 | V10: =IF(T10=0,0,SUMIFS($E:$E,$A:$A,$A10)/U10) -> 526.3913 | W10: =IF(V10=0,0,V10*1000000/I10) -> 12023557 | X10: =IF(W10=0,0,W10*J10) -> 1.578693e+08
A11: AAL | B11: 2017 | C11: Q2 | D11: 42916 | E11: 529 | F11: ytd_difference | G11: =IF(F11<>"missing","",IF(D11>DATE(2026,6,30),"not yet filed","no repurchases reported")) | H11: =A11&"-"&B11&"-"&C11 -> AAL-2017-Q2 | I11: =_xlfn.XLOOKUP(H11,prices!A:A,prices!F:F,"no match") -> 45.08 | J11: =_xlfn.XLOOKUP(A11,current!$A:$A,current!$B:$B,"no match") -> 13.13 | K11: =IF(E11="","",E11*1000000/I11) -> 11734694 | L11: =IF(K11="","",K11*J11) -> 1.5407653e+08 | M11: =IF(E11="","",E11*D11) -> 22702564 | N11: ="SPY-"&B11&"-"&C11 -> SPY-2017-Q2 | O11: =_xlfn.XLOOKUP(N11,prices!$A:$A,prices!$F:$F,"no match") -> 207.45 | P11: =IF(E11="","",E11*1000000/O11) -> 2550012.1 | Q11: =IF(P11="","",P11*assumptions!$B$4) -> 1.9639938e+09 | R11: =IF(E11="","",(TODAY()-D11)/365.25) -> 9.1909651 | S11: =IF(E11="","",E11*1000000*(1+assumptions!$B$3)^R11) -> 7.55247e+08 | T11: =IF(E11="",0,IF(E11>0,1,0)) -> 1 | U11: =SUMIFS($T:$T,$A:$A,$A11) -> 23 | V11: =IF(T11=0,0,SUMIFS($E:$E,$A:$A,$A11)/U11) -> 526.3913 | W11: =IF(V11=0,0,V11*1000000/I11) -> 11676826 | X11: =IF(W11=0,0,W11*J11) -> 1.5331672e+08
A12: AAL | B12: 2017 | C12: Q3 | D12: 43008 | E12: 359 | F12: ytd_difference | G12: =IF(F12<>"missing","",IF(D12>DATE(2026,6,30),"not yet filed","no repurchases reported")) | H12: =A12&"-"&B12&"-"&C12 -> AAL-2017-Q3 | I12: =_xlfn.XLOOKUP(H12,prices!A:A,prices!F:F,"no match") -> 47 | J12: =_xlfn.XLOOKUP(A12,current!$A:$A,current!$B:$B,"no match") -> 13.13 | K12: =IF(E12="","",E12*1000000/I12) -> 7638297.9 | L12: =IF(K12="","",K12*J12) -> 1.0029085e+08 | M12: =IF(E12="","",E12*D12) -> 15439872 | N12: ="SPY-"&B12&"-"&C12 -> SPY-2017-Q3 | O12: =_xlfn.XLOOKUP(N12,prices!$A:$A,prices!$F:$F,"no match") -> 214.46 | P12: =IF(E12="","",E12*1000000/O12) -> 1673971.8 | Q12: =IF(P12="","",P12*assumptions!$B$4) -> 1.2892764e+09 | R12: =IF(E12="","",(TODAY()-D12)/365.25) -> 8.9390828 | S12: =IF(E12="","",E12*1000000*(1+assumptions!$B$3)^R12) -> 5.0756304e+08 | T12: =IF(E12="",0,IF(E12>0,1,0)) -> 1 | U12: =SUMIFS($T:$T,$A:$A,$A12) -> 23 | V12: =IF(T12=0,0,SUMIFS($E:$E,$A:$A,$A12)/U12) -> 526.3913 | W12: =IF(V12=0,0,V12*1000000/I12) -> 11199815 | X12: =IF(W12=0,0,W12*J12) -> 1.4705357e+08
A13: AAL | B13: 2017 | C13: Q4 | D13: 43100 | E13: 243 | F13: ytd_difference | G13: =IF(F13<>"missing","",IF(D13>DATE(2026,6,30),"not yet filed","no repurchases reported")) | H13: =A13&"-"&B13&"-"&C13 -> AAL-2017-Q4 | I13: =_xlfn.XLOOKUP(H13,prices!A:A,prices!F:F,"no match") -> 48.51 | J13: =_xlfn.XLOOKUP(A13,current!$A:$A,current!$B:$B,"no match") -> 13.13 | K13: =IF(E13="","",E13*1000000/I13) -> 5009276.4 | L13: =IF(K13="","",K13*J13) -> 65771800 | M13: =IF(E13="","",E13*D13) -> 10473300 | N13: ="SPY-"&B13&"-"&C13 -> SPY-2017-Q4 | O13: =_xlfn.XLOOKUP(N13,prices!$A:$A,prices!$F:$F,"no match") -> 227.33 | P13: =IF(E13="","",E13*1000000/O13) -> 1068930.6 | Q13: =IF(P13="","",P13*assumptions!$B$4) -> 8.2327968e+08 | R13: =IF(E13="","",(TODAY()-D13)/365.25) -> 8.6872005 | S13: =IF(E13="","",E13*1000000*(1+assumptions!$B$3)^R13) -> 3.4022328e+08 | T13: =IF(E13="",0,IF(E13>0,1,0)) -> 1 | U13: =SUMIFS($T:$T,$A:$A,$A13) -> 23 | V13: =IF(T13=0,0,SUMIFS($E:$E,$A:$A,$A13)/U13) -> 526.3913 | W13: =IF(V13=0,0,V13*1000000/I13) -> 10851192 | X13: =IF(W13=0,0,W13*J13) -> 1.4247615e+08
... A277: JBLU | B277: 2026 | C277: Q2 | D277: 46203 | E277: 0 | F277: no line item filed | G277: =IF(F277<>"missing","",IF(D277>DATE(2026,6,30),"not yet filed","no repurchases reported")) | H277: =A277&"-"&B277&"-"&C277 -> JBLU-2026-Q2 | I277: =_xlfn.XLOOKUP(H277,prices!A:A,prices!F:F,"no match") -> 5.09 | J277: =_xlfn.XLOOKUP(A277,current!$A:$A,current!$B:$B,"no match") -> 4.63 | K277: =IF(E277="","",E277*1000000/I277) -> 0 | L277: =IF(K277="","",K277*J277) -> 0 | M277: =IF(E277="","",E277*D277) -> 0 | N277: ="SPY-"&B277&"-"&C277 -> SPY-2026-Q2 | O277: =_xlfn.XLOOKUP(N277,prices!$A:$A,prices!$F:$F,"no match") -> 723.39 | P277: =IF(E277="","",E277*1000000/O277) -> 0 | Q277: =IF(P277="","",P277*assumptions!$B$4) -> 0 | R277: =IF(E277="","",(TODAY()-D277)/365.25) -> 0.19164956 | S277: =IF(E277="","",E277*1000000*(1+assumptions!$B$3)^R277) -> 0 | T277: =IF(E277="",0,IF(E277>0,1,0)) -> 0 | U277: =SUMIFS($T:$T,$A:$A,$A277) -> 8 | V277: =IF(T277=0,0,SUMIFS($E:$E,$A:$A,$A277)/U277) -> 0 | W277: =IF(V277=0,0,V277*1000000/I277) -> 0 | X277: =IF(W277=0,0,W277*J277) -> 0

Sheet summary
A1: ticker | B1: total_spent_musd | C1: total_shares | D1: value_today_musd | E1: gain_loss_musd | F1: avg_price_paid | G1: return_pct | H1: avg_spend_date | I1: years_elapsed | J1: annualized_pct | K1: spy_value_musd | L1: debt_value_musd | M1: vs_spy_musd | N1: vs_debt_musd | O1: even_value_musd | P1: timing_alpha_musd | Q1: timing_alpha_pct
A2: AAL | B2: =SUMIFS(buybacks!$E:$E,buybacks!$A:$A,$A2) -> 12107 | C2: =SUMIFS(buybacks!$K:$K,buybacks!$A:$A,$A2) -> 3.1837389e+08 | D2: =SUMIFS(buybacks!$L:$L,buybacks!$A:$A,$A2)/1000000 -> 4180.2492 | E2: =D2-B2 -> -7926.7508 | F2: =B2*1000000/C2 -> 38.027615 | G2: =D2/B2-1 -> -0.6547246 | H2: =SUMIFS(buybacks!$M:$M,buybacks!$A:$A,$A2)/B2 -> 42694.074 | I2: =(TODAY()-H2)/365.25 -> 9.7985667 | J2: =(D2/B2)^(1/I2)-1 -> -0.10284568 | K2: =SUMIFS(buybacks!$Q:$Q,buybacks!$A:$A,$A2)/1000000 -> 49644.083 | L2: =SUMIFS(buybacks!$S:$S,buybacks!$A:$A,$A2)/1000000 -> 17717.607 | M2: =D2-K2 -> -45463.833 | N2: =D2-L2 -> -13537.358 | O2: =SUMIFS(buybacks!$X:$X,buybacks!$A:$A,$A2)/1000000 -> 5308.8704 | P2: =D2-O2 -> -1128.6211 | Q2: =D2/O2-1 -> -0.21259158
A3: ALK | B3: =SUMIFS(buybacks!$E:$E,buybacks!$A:$A,$A3) -> 2198 | C3: =SUMIFS(buybacks!$K:$K,buybacks!$A:$A,$A3) -> 41442996 | D3: =SUMIFS(buybacks!$L:$L,buybacks!$A:$A,$A3)/1000000 -> 1742.2636 | E3: =D3-B3 -> -455.73643 | F3: =B3*1000000/C3 -> 53.036706 | G3: =D3/B3-1 -> -0.20734142 | H3: =SUMIFS(buybacks!$M:$M,buybacks!$A:$A,$A3)/B3 -> 44394.333 | I3: =(TODAY()-H3)/365.25 -> 5.1435111 | J3: =(D3/B3)^(1/I3)-1 -> -0.044170653 | K3: =SUMIFS(buybacks!$Q:$Q,buybacks!$A:$A,$A3)/1000000 -> 5695.7566 | L3: =SUMIFS(buybacks!$S:$S,buybacks!$A:$A,$A3)/1000000 -> 2723.9004 | M3: =D3-K3 -> -3953.4931 | N3: =D3-L3 -> -981.63679 | O3: =SUMIFS(buybacks!$X:$X,buybacks!$A:$A,$A3)/1000000 -> 1707.4745 | P3: =D3-O3 -> 34.789072 | Q3: =D3/O3-1 -> 0.020374578
A4: DAL | B4: =SUMIFS(buybacks!$E:$E,buybacks!$A:$A,$A4) -> 10424 | C4: =SUMIFS(buybacks!$K:$K,buybacks!$A:$A,$A4) -> 2.4161051e+08 | D4: =SUMIFS(buybacks!$L:$L,buybacks!$A:$A,$A4)/1000000 -> 19369.915 | E4: =D4-B4 -> 8945.9148 | F4: =B4*1000000/C4 -> 43.143818 | G4: =D4/B4-1 -> 0.85820365 | H4: =SUMIFS(buybacks!$M:$M,buybacks!$A:$A,$A4)/B4 -> 42920.296 | I4: =(TODAY()-H4)/365.25 -> 9.1792021 | J4: =(D4/B4)^(1/I4)-1 -> 0.069831903 | K4: =SUMIFS(buybacks!$Q:$Q,buybacks!$A:$A,$A4)/1000000 -> 39542.617 | L4: =SUMIFS(buybacks!$S:$S,buybacks!$A:$A,$A4)/1000000 -> 14900.061 | M4: =D4-K4 -> -20172.702 | N4: =D4-L4 -> 4469.8541 | O4: =SUMIFS(buybacks!$X:$X,buybacks!$A:$A,$A4)/1000000 -> 18767.098 | P4: =D4-O4 -> 602.8164 | Q4: =D4/O4-1 -> 0.032120916
A5: JBLU | B5: =SUMIFS(buybacks!$E:$E,buybacks!$A:$A,$A5) -> 1570 | C5: =SUMIFS(buybacks!$K:$K,buybacks!$A:$A,$A5) -> 85263319 | D5: =SUMIFS(buybacks!$L:$L,buybacks!$A:$A,$A5)/1000000 -> 394.76917 | E5: =D5-B5 -> -1175.2308 | F5: =B5*1000000/C5 -> 18.413545 | G5: =D5/B5-1 -> -0.74855467 | H5: =SUMIFS(buybacks!$M:$M,buybacks!$A:$A,$A5)/B5 -> 43475.42 | I5: =(TODAY()-H5)/365.25 -> 7.6593556 | J5: =(D5/B5)^(1/I5)-1 -> -0.16493104 | K5: =SUMIFS(buybacks!$Q:$Q,buybacks!$A:$A,$A5)/1000000 -> 4892.2704 | L5: =SUMIFS(buybacks!$S:$S,buybacks!$A:$A,$A5)/1000000 -> 2114.7515 | M5: =D5-K5 -> -4497.5012 | N5: =D5-L5 -> -1719.9823 | O5: =SUMIFS(buybacks!$X:$X,buybacks!$A:$A,$A5)/1000000 -> 388.25349 | P5: =D5-O5 -> 6.5156798 | Q5: =D5/O5-1 -> 0.016782025
A6: LUV | B6: =SUMIFS(buybacks!$E:$E,buybacks!$A:$A,$A6) -> 13031 | C6: =SUMIFS(buybacks!$K:$K,buybacks!$A:$A,$A6) -> 3.2655685e+08 | D6: =SUMIFS(buybacks!$L:$L,buybacks!$A:$A,$A6)/1000000 -> 12938.183 | E6: =D6-B6 -> -92.817434 | F6: =B6*1000000/C6 -> 39.904231 | G6: =D6/B6-1 -> -0.0071228174 | H6: =SUMIFS(buybacks!$M:$M,buybacks!$A:$A,$A6)/B6 -> 43953.892 | I6: =(TODAY()-H6)/365.25 -> 6.3493707 | J6: =(D6/B6)^(1/I6)-1 -> -0.0011251955 | K6: =SUMIFS(buybacks!$Q:$Q,buybacks!$A:$A,$A6)/1000000 -> 37501.223 | L6: =SUMIFS(buybacks!$S:$S,buybacks!$A:$A,$A6)/1000000 -> 16841.561 | M6: =D6-K6 -> -24563.04 | N6: =D6-L6 -> -3903.3787 | O6: =SUMIFS(buybacks!$X:$X,buybacks!$A:$A,$A6)/1000000 -> 12762.789 | P6: =D6-O6 -> 175.39358 | Q6: =D6/O6-1 -> 0.013742574
A7: UAL | B7: =SUMIFS(buybacks!$E:$E,buybacks!$A:$A,$A7) -> 9750 | C7: =SUMIFS(buybacks!$K:$K,buybacks!$A:$A,$A7) -> 1.5103633e+08 | D7: =SUMIFS(buybacks!$L:$L,buybacks!$A:$A,$A7)/1000000 -> 16822.426 | E7: =D7-B7 -> 7072.4263 | F7: =B7*1000000/C7 -> 64.554006 | G7: =D7/B7-1 -> 0.72537705 | H7: =SUMIFS(buybacks!$M:$M,buybacks!$A:$A,$A7)/B7 -> 43192.634 | I7: =(TODAY()-H7)/365.25 -> 8.4335826 | J7: =(D7/B7)^(1/I7)-1 -> 0.066812716 | K7: =SUMIFS(buybacks!$Q:$Q,buybacks!$A:$A,$A7)/1000000 -> 34885.113 | L7: =SUMIFS(buybacks!$S:$S,buybacks!$A:$A,$A7)/1000000 -> 13580.045 | M7: =D7-K7 -> -18062.687 | N7: =D7-L7 -> 3242.3816 | O7: =SUMIFS(buybacks!$X:$X,buybacks!$A:$A,$A7)/1000000 -> 15618.728 | P7: =D7-O7 -> 1203.6981 | Q7: =D7/O7-1 -> 0.077067616

Sheet leverage_2019
A1: ticker | B1: operating_income | C1: d_and_a | D1: lt_debt_noncurrent | E1: lt_debt_current | F1: lease_noncurrent | G1: lease_current | H1: cash | I1: short_term_investments | J1: ebitda | K1: total_debt | L1: liquid_assets | M1: net_debt | N1: net_debt_ebitda | O1: source
A2: DAL | B2: 6618 | C2: 2581 | D2: 8052 | E2: 2054 | F2: 5294 | G2: 801 | H2: 2882 | I2: 0 | J2: =B2+C2 -> 9199 | K2: =D2+E2+F2+G2 -> 16201 | L2: =H2+I2 -> 2882 | M2: =K2-L2 -> 13319 | N2: =M2/J2 -> 1.4478748 | O2: FY2019 10-K, balance sheet + income statement
A3: UAL | B3: 4301 | C3: 2288 | D3: 13145 | E3: 1407 | F3: 4946 | G3: 686 | H3: 2762 | I3: 2182 | J3: =B3+C3 -> 6589 | K3: =D3+E3+F3+G3 -> 20184 | L3: =H3+I3 -> 4944 | M3: =K3-L3 -> 15240 | N3: =M3/J3 -> 2.3129458 | O3: FY2019 10-K, balance sheet + income statement
A4: AAL | B4: 3065 | C4: 2600 | D4: 21454 | E4: 2749 | F4: 7421 | G4: 1708 | H4: 280 | I4: 3546 | J4: =B4+C4 -> 5665 | K4: =D4+E4+F4+G4 -> 33332 | L4: =H4+I4 -> 3826 | M4: =K4-L4 -> 29506 | N4: =M4/J4 -> 5.2084731 | O4: FY2019 10-K; debt from long-term debt note
A5: LUV | B5: 2957 | C5: 1219 | D5: 1846 | E5: 819 | F5: 978 | G5: 353 | H5: 2548 | I5: 1524 | J5: =B5+C5 -> 4176 | K5: =D5+E5+F5+G5 -> 3996 | L5: =H5+I5 -> 4072 | M5: =K5-L5 -> -76 | N5: =M5/J5 -> -0.018199234 | O5: FY2019 10-K; debt from long-term debt note
A6: ALK | B6: 1063 | C6: 423 | D6: 1264 | E6: 235 | F6: 1439 | G6: 269 | H6: 221 | I6: 1300 | J6: =B6+C6 -> 1486 | K6: =D6+E6+F6+G6 -> 3207 | L6: =H6+I6 -> 1521 | M6: =K6-L6 -> 1686 | N6: =M6/J6 -> 1.1345895 | O6: FY2019 10-K, balance sheet + income statement
A7: JBLU | B7: 800 | C7: 525 | D7: 1990 | E7: 344 | F7: 690 | G7: 128 | H7: 959 | I7: 369 | J7: =B7+C7 -> 1325 | K7: =D7+E7+F7+G7 -> 3152 | L7: =H7+I7 -> 1328 | M7: =K7-L7 -> 1824 | N7: =M7/J7 -> 1.3766038 | O7: FY2019 10-K; debt from long-term debt note

Sheet prices
A1: key | B1: ticker | C1: fiscal_year | D1: quarter | E1: period_end | F1: avg_price | G1: trading_days | H1: complete_quarter
A2: AAL-2015-Q1 | B2: AAL | C2: 2015 | D2: Q1 | E2: 42094 | F2: 48.17 | G2: 61 | H2: TRUE
A3: AAL-2015-Q2 | B3: AAL | C3: 2015 | D3: Q2 | E3: 42185 | F3: 43.35 | G3: 63 | H3: TRUE
A4: AAL-2015-Q3 | B4: AAL | C4: 2015 | D4: Q3 | E4: 42277 | F4: 39.12 | G4: 64 | H4: TRUE
A5: AAL-2015-Q4 | B5: AAL | C5: 2015 | D5: Q4 | E5: 42369 | F5: 41.38 | G5: 64 | H5: TRUE
A6: AAL-2016-Q1 | B6: AAL | C6: 2016 | D6: Q1 | E6: 42460 | F6: 38.53 | G6: 61 | H6: TRUE
A7: AAL-2016-Q2 | B7: AAL | C7: 2016 | D7: Q2 | E7: 42551 | F7: 32.44 | G7: 64 | H7: TRUE
A8: AAL-2016-Q3 | B8: AAL | C8: 2016 | D8: Q3 | E8: 42643 | F8: 34.02 | G8: 64 | H8: TRUE
A9: AAL-2016-Q4 | B9: AAL | C9: 2016 | D9: Q4 | E9: 42735 | F9: 42.05 | G9: 63 | H9: TRUE
A10: AAL-2017-Q1 | B10: AAL | C10: 2017 | D10: Q1 | E10: 42825 | F10: 43.78 | G10: 62 | H10: TRUE
A11: AAL-2017-Q2 | B11: AAL | C11: 2017 | D11: Q2 | E11: 42916 | F11: 45.08 | G11: 63 | H11: TRUE
A12: AAL-2017-Q3 | B12: AAL | C12: 2017 | D12: Q3 | E12: 43008 | F12: 47 | G12: 63 | H12: TRUE
A13: AAL-2017-Q4 | B13: AAL | C13: 2017 | D13: Q4 | E13: 43100 | F13: 48.51 | G13: 63 | H13: TRUE
... A330: UAL-2026-Q3 | B330: UAL | C330: 2026 | D330: Q3 | E330: 46295 | F330: 120.7 | G330: 47 | H330: FALSE

Sheet current
A1: ticker | B1: current_price | C1: as_of_date
A2: AAL | B2: 13.13 | C2: 46269
A3: ALK | B3: 42.04 | C3: 46269
A4: DAL | B4: 80.17 | C4: 46269
A5: JBLU | B5: 4.63 | C5: 46269
A6: LUV | B6: 39.62 | C6: 46269
A7: SPY | B7: 770.19 | C7: 46269
A8: UAL | B8: 111.38 | C8: 46269

Sheet assumptions
A1: cost_of_debt_pretax | B1: 0.05 | C1: Weighted avg coupon, 2015-2019 10-K debt footnotes
A2: tax_rate | B2: 0.21 | C2: US federal statutory rate, post-2017
A3: cost_of_debt_aftertax | B3: =B1*(1-B2) -> 0.0395 | C3: Calculated from B1 and B2
A4: spy_current_price | B4: =_xlfn.XLOOKUP("SPY",current!A:A,current!B:B) -> 770.19 | C4: Yahoo Finance close, via yfinance
A5: as_of_date | B5: =_xlfn.XLOOKUP("SPY",current!A:A,current!C:C) -> 46269 | C5: Yahoo Finance, most recent trading day
